lineshape_tools-0.1.0.dist-info/METADATA
lineshape_tools-0.1.0.dist-info/WHEEL
lineshape_tools-0.1.0.dist-info/entry_points.txt
lineshape_tools-0.1.0.dist-info/licenses/LICENSE
lineshape_tools/__init__.py
lineshape_tools/__main__.py
lineshape_tools/cli.py
lineshape_tools/constants.py
lineshape_tools/lineshape.py
lineshape_tools/phonon.py
lineshape_tools/plot.py
lineshape_tools-0.1.0.dist-info/RECORD
