Metadata-Version: 2.1
Name: lineshape_tools
Version: 0.1.0
Summary: Software to evaluate the optical lineshape function of a defect.
Keywords: defect,luminescence,absorption,electron-phonon coupling,density functional theory
Author-Email: "Mark E. Turiansky" <mark.e.turiansky.ctr@us.navy.mil>
License: MIT
Classifier: Topic :: Scientific/Engineering
Classifier: Topic :: Scientific/Engineering :: Physics
Classifier: License :: OSI Approved :: MIT License
Classifier: Programming Language :: Python :: 3
Classifier: Programming Language :: Python :: 3.10
Classifier: Programming Language :: Python :: 3.11
Classifier: Programming Language :: Python :: 3.12
Classifier: Programming Language :: Python :: 3.13
Project-URL: Homepage, https://github.com/mturiansky/lineshape_tools
Project-URL: Documentation, https://lineshape_tools.readthedocs.io/en/latest
Project-URL: Repository, https://github.com/mturiansky/lineshape_tools.git
Project-URL: Issues, https://github.com/mturiansky/lineshape_tools/issues
Requires-Python: <3.14,>=3.10
Requires-Dist: mace-torch>=0.3.10
Requires-Dist: numpy>=1.26.4
Requires-Dist: numba>=0.61.0
Requires-Dist: rocket-fft>=0.2.5
Requires-Dist: cyclopts>=3.16.1
Requires-Dist: ase>=3.25.0
Requires-Dist: scipy>=1.15.3
Requires-Dist: tqdm>=4.67.1
Provides-Extra: extra
Requires-Dist: phonopy>=2.42.0; extra == "extra"
Requires-Dist: matplotlib>=3.10.5; extra == "extra"
